win32_scdump/Scylla.dll
win32_scdump/__init__.py
win32_scdump/main.py
win32_scdump/scylla_pd.exe
win32_scdump-0.1.0.dist-info/LICENSE
win32_scdump-0.1.0.dist-info/METADATA
win32_scdump-0.1.0.dist-info/WHEEL
win32_scdump-0.1.0.dist-info/entry_points.txt
win32_scdump-0.1.0.dist-info/top_level.txt
win32_scdump-0.1.0.dist-info/RECORD
