Metadata-Version: 2.1
Name: win32-scdump
Version: 0.1.0
Summary: Scylla Process Dumper is a lightweight and easy-to-use debugging tool designed to create dumps of running processes on Windows using Scylla
Author: AleirJDawn
Author-email: 
Classifier: Programming Language :: Python :: 3
Classifier: License :: OSI Approved :: MIT License
Requires-Python: >=3.6
License-File: LICENSE
